AltAnalyze3-0.1.2.data/scripts/altanalyze3
altanalyze3/__init__.py
altanalyze3/bin/__init__.py
altanalyze3/bin/altanalyze3
altanalyze3/components/__init__.py
altanalyze3/components/aggregate/__init__.py
altanalyze3/components/aggregate/main.py
altanalyze3/components/annotation/__init__.py
altanalyze3/components/annotation/ensembl_biomart.py
altanalyze3/components/annotation/junction_isoform.py
altanalyze3/components/gene_model/__init__.py
altanalyze3/components/gene_model/gene_model.py
altanalyze3/components/intron_count/__init__.py
altanalyze3/components/intron_count/main.py
altanalyze3/components/junction_count/__init__.py
altanalyze3/components/junction_count/main.py
altanalyze3/components/long_read/__init__.py
altanalyze3/components/long_read/comparisons.py
altanalyze3/components/long_read/gff_process.py
altanalyze3/components/long_read/isoform_automate.py
altanalyze3/components/long_read/isoform_junctions.py
altanalyze3/components/long_read/isoform_junctions_chunk.py
altanalyze3/components/long_read/isoform_matrix.py
altanalyze3/components/long_read/isoform_ratios.py
altanalyze3/components/long_read/isoform_snv.py
altanalyze3/components/long_read/isoform_translation.py
altanalyze3/components/oncosplice/PCAbasedFeatureSelection.py
altanalyze3/components/oncosplice/RoundWrapper.py
altanalyze3/components/oncosplice/__init__.py
altanalyze3/components/oncosplice/correlationDepletion.py
altanalyze3/components/oncosplice/determineNMFRank.py
altanalyze3/components/oncosplice/linearSVM.py
altanalyze3/components/oncosplice/main.py
altanalyze3/components/oncosplice/medianImpute.py
altanalyze3/components/oncosplice/metadataAnalysis.py
altanalyze3/components/oncosplice/preprocess.py
altanalyze3/components/oncosplice/removeRedundantSplicingEvents.py
altanalyze3/components/oncosplice/runNMF.py
altanalyze3/components/oncosplice/visualizations.py
altanalyze3/components/psi/__init__.py
altanalyze3/components/psi/main.py
altanalyze3/components/psi/main_backup.py
AltAnalyze3-0.1.2.dist-info/LICENSE
AltAnalyze3-0.1.2.dist-info/METADATA
AltAnalyze3-0.1.2.dist-info/WHEEL
AltAnalyze3-0.1.2.dist-info/top_level.txt
AltAnalyze3-0.1.2.dist-info/RECORD
