Metadata-Version: 2.1
Name: AltAnalyze3
Version: 0.1.2
Summary: AltAnalyze3: Advanced RNA-Seq Analysis Workflow
Home-page: https://github.com/SalomonisLab/altanalyze3.git
Author: AltAnalyze Development Team
Author-email: AltAnalyze <altanalyze@gmail.com>
License: Apache-2.0
Classifier: Environment :: Console
Classifier: Intended Audience :: Developers
Classifier: Intended Audience :: Science/Research
Classifier: License :: OSI Approved :: Apache Software License
Classifier: Topic :: Scientific/Engineering :: Bio-Informatics
License-File: LICENSE
Requires-Dist: aiofiles ==24.1.0
Requires-Dist: anndata ==0.10.9
Requires-Dist: Bio ==1.7.1
Requires-Dist: biopython >=1.84
Requires-Dist: future ==1.0.0
Requires-Dist: h5py ==3.10.0
Requires-Dist: joblib ==1.3.2
Requires-Dist: matplotlib ==3.6.2
Requires-Dist: nimfa ==1.4.0
Requires-Dist: numpy ==1.23.5
Requires-Dist: pandas ==1.5.2
Requires-Dist: pysam ==0.22.0
Requires-Dist: pytest ==8.3.3
Requires-Dist: requests ==2.32.3
Requires-Dist: scanpy ==1.10.3
Requires-Dist: scikit-learn ==1.3.2
Requires-Dist: scipy ==1.14.1
Requires-Dist: setuptools ==68.2.2
Requires-Dist: statsmodels ==0.14.0
Requires-Dist: tqdm ==4.62.3
